{
  "__ar": 1,
  "payload": null,
  "jsmods": {
    "require": [
      [
        "UFICentralUpdates",
        "handleUpdate",
        [],
        [
          19,
          {
            "feedbacktargets": [],
            "comments": [
              {
                "body": {
                  "text": "New catch phrase: instead of \"let's take this offline\", it's now \"let's take this to John coates 2k7\"",
                  "ranges": [],
                  "aggregatedranges": []
                },
                "isfeatured": false,
                "likecount": 3,
                "hasviewerliked": false,
                "canremove": false,
                "canreport": true,
                "canedit": false,
                "isauthorweakreference": false,
                "istranslatable": false,
                "viewercanlike": true,
                "cancomment": false,
                "spamreplycount": 0,
                "commentshareuri": "/ajax/sharer/?s=69&appid=435066949857522&id=10102635622638481&p%5B0%5D=10102635622638481",
                "id": "508184482641_10102635622638481",
                "fbid": "10102635622638481",
                "legacyid": "10102635622638481",
                "author": "591234151",
                "ftentidentifier": "508184482641",
                "source": 3,
                "highlightcomment": false,
                "timestamp": {
                  "time": 1459882614,
                  "text": "",
                  "verbose": "Tuesday, 5 April 2016 at 20:56"
                }
              },
              {
                "body": {
                  "text": "facebook feature request: offline sync this thread",
                  "ranges": [],
                  "aggregatedranges": []
                },
                "isfeatured": false,
                "likecount": 2,
                "hasviewerliked": false,
                "canremove": false,
                "canreport": true,
                "canedit": false,
                "isauthorweakreference": false,
                "istranslatable": false,
                "viewercanlike": true,
                "cancomment": false,
                "spamreplycount": 0,
                "commentshareuri": "/ajax/sharer/?s=69&appid=435066949857522&id=10102635622937881&p%5B0%5D=10102635622937881",
                "id": "508184482641_10102635622937881",
                "fbid": "10102635622937881",
                "legacyid": "10102635622937881",
                "author": "689412686",
                "ftentidentifier": "508184482641",
                "source": 1,
                "highlightcomment": false,
                "timestamp": {
                  "time": 1459882638,
                  "text": "",
                  "verbose": "Tuesday, 5 April 2016 at 20:57"
                }
              },
              {
                "body": {
                  "text": "so i can read the comments from takeoff to touchdown",
                  "ranges": [],
                  "aggregatedranges": []
                },
                "isfeatured": false,
                "likecount": 0,
                "hasviewerliked": false,
                "canremove": false,
                "canreport": true,
                "canedit": false,
                "isauthorweakreference": false,
                "istranslatable": false,
                "viewercanlike": true,
                "cancomment": false,
                "spamreplycount": 0,
                "commentshareuri": "/ajax/sharer/?s=69&appid=435066949857522&id=10102635623681391&p%5B0%5D=10102635623681391",
                "id": "508184482641_10102635623681391",
                "fbid": "10102635623681391",
                "legacyid": "10102635623681391",
                "author": "689412686",
                "ftentidentifier": "508184482641",
                "source": 1,
                "highlightcomment": false,
                "timestamp": {
                  "time": 1459882674,
                  "text": "",
                  "verbose": "Tuesday, 5 April 2016 at 20:57"
                }
              },
              {
                "body": {
                  "text": "True story: security dude turns off the lights in the office at precisely 9pm",
                  "ranges": [],
                  "aggregatedranges": []
                },
                "isfeatured": false,
                "likecount": 1,
                "hasviewerliked": false,
                "canremove": false,
                "canreport": true,
                "canedit": false,
                "isauthorweakreference": false,
                "istranslatable": false,
                "viewercanlike": true,
                "cancomment": false,
                "spamreplycount": 0,
                "commentshareuri": "/ajax/sharer/?s=69&appid=435066949857522&id=10102635625248251&p%5B0%5D=10102635625248251",
                "id": "508184482641_10102635625248251",
                "fbid": "10102635625248251",
                "legacyid": "10102635625248251",
                "author": "591234151",
                "ftentidentifier": "508184482641",
                "source": 1,
                "highlightcomment": false,
                "timestamp": {
                  "time": 1459882764,
                  "text": "",
                  "verbose": "Tuesday, 5 April 2016 at 20:59"
                }
              },
              {
                "body": {
                  "text": "New Darius Kilstein fireside chat idea: read out comments on this thread with imitations. Oliver can help you get past the 14552 hours track length limit.",
                  "ranges": [
                    {
                      "offset": 4,
                      "length": 15,
                      "entity": {
                        "url": "https://www.facebook.com/dkilstein",
                        "id": 738240163,
                        "type": "user"
                      }
                    },
                    {
                      "offset": 90,
                      "length": 6,
                      "entity": {
                        "url": "https://www.facebook.com/oliver.hookins",
                        "id": 689412686,
                        "type": "user"
                      }
                    }
                  ],
                  "aggregatedranges": []
                },
                "isfeatured": false,
                "likecount": 0,
                "hasviewerliked": false,
                "canremove": false,
                "canreport": true,
                "canedit": false,
                "isauthorweakreference": false,
                "istranslatable": false,
                "viewercanlike": true,
                "cancomment": false,
                "spamreplycount": 0,
                "commentshareuri": "/ajax/sharer/?s=69&appid=435066949857522&id=10102635629554621&p%5B0%5D=10102635629554621",
                "id": "508184482641_10102635629554621",
                "fbid": "10102635629554621",
                "legacyid": "10102635629554621",
                "author": "227701401",
                "ftentidentifier": "508184482641",
                "source": 2,
                "highlightcomment": false,
                "timestamp": {
                  "time": 1459883002,
                  "text": "",
                  "verbose": "Tuesday, 5 April 2016 at 21:03"
                }
              },
              {
                "body": {
                  "text": "I'm enjoying reading this thread on the way home",
                  "ranges": [],
                  "aggregatedranges": []
                },
                "isfeatured": false,
                "likecount": 0,
                "hasviewerliked": false,
                "canremove": false,
                "canreport": true,
                "canedit": false,
                "isauthorweakreference": false,
                "istranslatable": false,
                "viewercanlike": true,
                "cancomment": false,
                "spamreplycount": 0,
                "commentshareuri": "/ajax/sharer/?s=69&appid=435066949857522&id=10102635630153421&p%5B0%5D=10102635630153421",
                "id": "508184482641_10102635630153421",
                "fbid": "10102635630153421",
                "legacyid": "10102635630153421",
                "author": "23911310",
                "ftentidentifier": "508184482641",
                "source": 3,
                "highlightcomment": false,
                "timestamp": {
                  "time": 1459883040,
                  "text": "",
                  "verbose": "Tuesday, 5 April 2016 at 21:04"
                }
              },
              {
                "body": {
                  "text": "Slack's valuation is so fucked when the tech press get wind of this thread",
                  "ranges": [],
                  "aggregatedranges": []
                },
                "isfeatured": false,
                "likecount": 1,
                "hasviewerliked": false,
                "canremove": false,
                "canreport": true,
                "canedit": false,
                "isauthorweakreference": false,
                "istranslatable": false,
                "viewercanlike": true,
                "cancomment": false,
                "spamreplycount": 0,
                "commentshareuri": "/ajax/sharer/?s=69&appid=435066949857522&id=10102635630762201&p%5B0%5D=10102635630762201",
                "id": "508184482641_10102635630762201",
                "fbid": "10102635630762201",
                "legacyid": "10102635630762201",
                "author": "591234151",
                "ftentidentifier": "508184482641",
                "source": 17,
                "highlightcomment": false,
                "timestamp": {
                  "time": 1459883093,
                  "text": "",
                  "verbose": "Tuesday, 5 April 2016 at 21:04"
                }
              },
              {
                "body": {
                  "text": "Next gen collaboration is happening RIGHT HERE folks",
                  "ranges": [],
                  "aggregatedranges": []
                },
                "isfeatured": false,
                "likecount": 0,
                "hasviewerliked": false,
                "canremove": false,
                "canreport": true,
                "canedit": false,
                "isauthorweakreference": false,
                "istranslatable": false,
                "viewercanlike": true,
                "cancomment": false,
                "spamreplycount": 0,
                "commentshareuri": "/ajax/sharer/?s=69&appid=435066949857522&id=10102635631171381&p%5B0%5D=10102635631171381",
                "id": "508184482641_10102635631171381",
                "fbid": "10102635631171381",
                "legacyid": "10102635631171381",
                "author": "591234151",
                "ftentidentifier": "508184482641",
                "source": 17,
                "highlightcomment": false,
                "timestamp": {
                  "time": 1459883116,
                  "text": "",
                  "verbose": "Tuesday, 5 April 2016 at 21:05"
                }
              },
              {
                "body": {
                  "text": "Cole glad to hear you're enjoying this thread mate.",
                  "ranges": [
                    {
                      "offset": 0,
                      "length": 4,
                      "entity": {
                        "url": "https://www.facebook.com/cmercer1",
                        "id": 23911310,
                        "type": "user"
                      }
                    }
                  ],
                  "aggregatedranges": []
                },
                "isfeatured": false,
                "likecount": 1,
                "hasviewerliked": false,
                "canremove": false,
                "canreport": true,
                "canedit": false,
                "isauthorweakreference": false,
                "istranslatable": false,
                "viewercanlike": true,
                "cancomment": false,
                "spamreplycount": 0,
                "commentshareuri": "/ajax/sharer/?s=69&appid=435066949857522&id=10102635631425871&p%5B0%5D=10102635631425871",
                "id": "508184482641_10102635631425871",
                "fbid": "10102635631425871",
                "legacyid": "10102635631425871",
                "author": "227701401",
                "ftentidentifier": "508184482641",
                "source": 2,
                "highlightcomment": false,
                "timestamp": {
                  "time": 1459883126,
                  "text": "",
                  "verbose": "Tuesday, 5 April 2016 at 21:05"
                }
              },
              {
                "body": {
                  "text": "We've created a monster!",
                  "ranges": [],
                  "aggregatedranges": []
                },
                "isfeatured": false,
                "likecount": 0,
                "hasviewerliked": false,
                "canremove": false,
                "canreport": true,
                "canedit": false,
                "isauthorweakreference": false,
                "istranslatable": false,
                "viewercanlike": true,
                "cancomment": false,
                "spamreplycount": 0,
                "commentshareuri": "/ajax/sharer/?s=69&appid=435066949857522&id=10102635634005701&p%5B0%5D=10102635634005701",
                "id": "508184482641_10102635634005701",
                "fbid": "10102635634005701",
                "legacyid": "10102635634005701",
                "author": "1074174515",
                "ftentidentifier": "508184482641",
                "source": 3,
                "highlightcomment": false,
                "timestamp": {
                  "time": 1459883287,
                  "text": "",
                  "verbose": "Tuesday, 5 April 2016 at 21:08"
                }
              }
            ],
            "profiles": [
              {
                "id": "591234151",
                "name": "Nick Fisher",
                "firstName": "Nick",
                "vanity": "nickf2",
                "thumbSrc": "https://scontent.ftxl1-1.fna.fbcdn.net/hprofile-xal1/v/t1.0-1/c4.4.64.64/p74x74/16083_10151587099369152_1447425115_n.jpg?oh=1293e2962a801a77b4924c6c67477ea5&oe=57899015",
                "uri": "https://www.facebook.com/nickf2?fref=ufi",
                "gender": 2,
                "i18nGender": 16777216,
                "type": "friend",
                "is_friend": true
              },
              {
                "id": "689412686",
                "name": "Oliver Hookins",
                "firstName": "Oliver",
                "vanity": "oliver.hookins",
                "thumbSrc": "https://scontent.ftxl1-1.fna.fbcdn.net/hprofile-xtf1/v/t1.0-1/p64x64/1930350_10153230195892687_9007624726573013478_n.jpg?oh=93b2000391c4f2105fa76d9b6688810a&oe=578816CB",
                "uri": "https://www.facebook.com/oliver.hookins?fref=ufi",
                "gender": 2,
                "i18nGender": 16777216,
                "type": "user",
                "is_friend": false
              },
              {
                "id": "227701401",
                "name": "Sridhar Ravichandran",
                "firstName": "Sridhar",
                "vanity": "sridharancr",
                "thumbSrc": "https://scontent.ftxl1-1.fna.fbcdn.net/hprofile-xfp1/v/t1.0-1/c9.6.64.64/p80x80/12509813_748112546578_6358565704163338314_n.jpg?oh=f1d35f41395b95f1199487d951ef04b2&oe=5783D6CA",
                "uri": "https://www.facebook.com/sridharancr?fref=ufi",
                "gender": 2,
                "i18nGender": 16777216,
                "type": "user",
                "is_friend": false
              },
              {
                "id": "23911310",
                "name": "Cole Mercer",
                "firstName": "Cole",
                "vanity": "cmercer1",
                "thumbSrc": "https://scontent.ftxl1-1.fna.fbcdn.net/hprofile-xpf1/v/t1.0-1/p64x64/10881704_10103110093554620_8303054274959248956_n.jpg?oh=722425a4aa000418fd5bc4017d48f4ca&oe=578DFE51",
                "uri": "https://www.facebook.com/cmercer1?fref=ufi",
                "gender": 2,
                "i18nGender": 16777216,
                "type": "friend",
                "is_friend": true
              },
              {
                "id": "1074174515",
                "name": "Marcus Schaefer",
                "firstName": "Marcus",
                "vanity": "marcusschaefer",
                "thumbSrc": "https://scontent.ftxl1-1.fna.fbcdn.net/hprofile-xaf1/v/t1.0-1/p64x64/11079694_10204942647340626_3800591212246515075_n.jpg?oh=bd5559bd51ff57a16ef3d67da172b7f5&oe=577365FD",
                "uri": "https://www.facebook.com/marcusschaefer?fref=ufi",
                "gender": 2,
                "i18nGender": 16777216,
                "type": "user",
                "is_friend": false
              }
            ],
            "actions": [],
            "commentlists": {
              "comments": {
                "508184482641": {
                  "chronological": {
                    "range": {
                      "offset": 550,
                      "length": 10
                    },
                    "values": [
                      "508184482641_10102635622638481",
                      "508184482641_10102635622937881",
                      "508184482641_10102635623681391",
                      "508184482641_10102635625248251",
                      "508184482641_10102635629554621",
                      "508184482641_10102635630153421",
                      "508184482641_10102635630762201",
                      "508184482641_10102635631171381",
                      "508184482641_10102635631425871",
                      "508184482641_10102635634005701"
                    ],
                    "count": 571
                  }
                }
              },
              "replies": {
                "508184482641_10102635622638481": {
                  "range": {
                    "offset": 0,
                    "length": 0
                  },
                  "values": [],
                  "count": 0,
                  "ftentidentifier": 508184482641,
                  "containerorderingmode": "chronological"
                },
                "508184482641_10102635622937881": {
                  "range": {
                    "offset": 0,
                    "length": 0
                  },
                  "values": [],
                  "count": 0,
                  "ftentidentifier": 508184482641,
                  "containerorderingmode": "chronological"
                },
                "508184482641_10102635623681391": {
                  "range": {
                    "offset": 0,
                    "length": 0
                  },
                  "values": [],
                  "count": 0,
                  "ftentidentifier": 508184482641,
                  "containerorderingmode": "chronological"
                },
                "508184482641_10102635625248251": {
                  "range": {
                    "offset": 0,
                    "length": 0
                  },
                  "values": [],
                  "count": 0,
                  "ftentidentifier": 508184482641,
                  "containerorderingmode": "chronological"
                },
                "508184482641_10102635629554621": {
                  "range": {
                    "offset": 0,
                    "length": 0
                  },
                  "values": [],
                  "count": 0,
                  "ftentidentifier": 508184482641,
                  "containerorderingmode": "chronological"
                },
                "508184482641_10102635630153421": {
                  "range": {
                    "offset": 0,
                    "length": 0
                  },
                  "values": [],
                  "count": 0,
                  "ftentidentifier": 508184482641,
                  "containerorderingmode": "chronological"
                },
                "508184482641_10102635630762201": {
                  "range": {
                    "offset": 0,
                    "length": 0
                  },
                  "values": [],
                  "count": 0,
                  "ftentidentifier": 508184482641,
                  "containerorderingmode": "chronological"
                },
                "508184482641_10102635631171381": {
                  "range": {
                    "offset": 0,
                    "length": 0
                  },
                  "values": [],
                  "count": 0,
                  "ftentidentifier": 508184482641,
                  "containerorderingmode": "chronological"
                },
                "508184482641_10102635631425871": {
                  "range": {
                    "offset": 0,
                    "length": 0
                  },
                  "values": [],
                  "count": 0,
                  "ftentidentifier": 508184482641,
                  "containerorderingmode": "chronological"
                },
                "508184482641_10102635634005701": {
                  "range": {
                    "offset": 0,
                    "length": 0
                  },
                  "values": [],
                  "count": 0,
                  "ftentidentifier": 508184482641,
                  "containerorderingmode": "chronological"
                }
              }
            },
            "featuredcommentlists": {
              "comments": null,
              "replies": null
            },
            "servertime": 1459885420
          }
        ],
        []
      ]
    ]
  },
  "css": [
    "ChMB+"
  ],
  "js": [
    "/NqAA",
    "ThKmv",
    "7+Wvj",
    "RVoyp"
  ],
  "bootloadable": {
    "AsyncSignal": {
      "resources": [
        "/NqAA",
        "ChMB+"
      ],
      "module": 1
    },
    "XLinkshimLogController": {
      "resources": [
        "/NqAA",
        "ThKmv",
        "oeUXN"
      ],
      "module": 1
    },
    "ExceptionDialog": {
      "resources": [
        "/NqAA",
        "vjV9S",
        "ChMB+",
        "ThKmv",
        "GHhcl",
        "RVoyp",
        "xRvqJ",
        "M99oK",
        "nyijU",
        "xxecq"
      ],
      "module": 1
    },
    "React": {
      "resources": [
        "RVoyp",
        "ThKmv",
        "/NqAA",
        "ChMB+"
      ],
      "module": 1
    },
    "AsyncDOM": {
      "resources": [
        "/NqAA",
        "ChMB+",
        "kCdR4"
      ],
      "module": 1
    },
    "ConfirmationDialog": {
      "resources": [
        "/NqAA",
        "ChMB+",
        "oE4Do"
      ],
      "module": 1
    },
    "Dialog": {
      "resources": [
        "/NqAA",
        "ThKmv",
        "ChMB+",
        "vjV9S",
        "nyijU",
        "PnFXr"
      ],
      "module": 1
    },
    "QuickSandSolver": {
      "resources": [
        "/NqAA",
        "ChMB+",
        "PNiUp",
        "ccpBO",
        "ThKmv",
        "sHjT1",
        "+ClWy"
      ],
      "module": 1
    },
    "ErrorSignal": {
      "resources": [
        "/NqAA",
        "ChMB+",
        "cNca2"
      ],
      "module": 1
    },
    "ReactDOM": {
      "resources": [
        "RVoyp",
        "ThKmv",
        "/NqAA",
        "ChMB+"
      ],
      "module": 1
    }
  },
  "resource_map": {
    "/NqAA": {
      "type": "js",
      "src": "https://static.xx.fbcdn.net/rsrc.php/v2iWxT3/yx/l/en_GB/HROIdTujVmr.js",
      "crossOrigin": 1
    },
    "ChMB+": {
      "type": "css",
      "src": "https://static.xx.fbcdn.net/rsrc.php/v2/yx/r/k3Q2XVxSzbX.css",
      "permanent": 1,
      "crossOrigin": 1
    },
    "ThKmv": {
      "type": "js",
      "src": "https://static.xx.fbcdn.net/rsrc.php/v2icMq3/yq/l/en_GB/aDAQ5kMH0Pn.js",
      "crossOrigin": 1
    },
    "oeUXN": {
      "type": "js",
      "src": "https://static.xx.fbcdn.net/rsrc.php/v2/yZ/r/aBvqchyj98N.js",
      "crossOrigin": 1
    },
    "vjV9S": {
      "type": "js",
      "src": "https://static.xx.fbcdn.net/rsrc.php/v2iXqO3/yy/l/en_GB/gr9cOlHfR7a.js",
      "crossOrigin": 1
    },
    "GHhcl": {
      "type": "css",
      "src": "https://static.xx.fbcdn.net/rsrc.php/v2/yD/r/M1T65RA6tXh.css",
      "permanent": 1,
      "crossOrigin": 1
    },
    "RVoyp": {
      "type": "js",
      "src": "https://static.xx.fbcdn.net/rsrc.php/v2iwdk3/yW/l/en_GB/1knLCNg5RDa.js",
      "crossOrigin": 1
    },
    "xRvqJ": {
      "type": "js",
      "src": "https://static.xx.fbcdn.net/rsrc.php/v2ixjD3/yL/l/en_GB/G9SciDaoLgv.js",
      "crossOrigin": 1
    },
    "M99oK": {
      "type": "js",
      "src": "https://static.xx.fbcdn.net/rsrc.php/v2i6Fo3/yT/l/en_GB/irADvQCTTxL.js",
      "crossOrigin": 1
    },
    "nyijU": {
      "type": "css",
      "src": "https://static.xx.fbcdn.net/rsrc.php/v2/yi/r/nGIJR7qmC-t.css",
      "permanent": 1,
      "crossOrigin": 1
    },
    "xxecq": {
      "type": "js",
      "src": "https://static.xx.fbcdn.net/rsrc.php/v2iEvA3/y5/l/en_GB/vZhgfyaOfr4.js",
      "crossOrigin": 1
    },
    "kCdR4": {
      "type": "js",
      "src": "https://static.xx.fbcdn.net/rsrc.php/v2/yn/r/JzB2tsQVw-3.js",
      "crossOrigin": 1
    },
    "oE4Do": {
      "type": "js",
      "src": "https://static.xx.fbcdn.net/rsrc.php/v2/yq/r/g65Ifm-JIn6.js",
      "crossOrigin": 1
    },
    "PnFXr": {
      "type": "js",
      "src": "https://static.xx.fbcdn.net/rsrc.php/v2i55M3/yA/l/en_GB/W1TltFpUoyK.js",
      "crossOrigin": 1
    },
    "PNiUp": {
      "type": "js",
      "src": "https://static.xx.fbcdn.net/rsrc.php/v2/ys/r/m5QDGyZX8QU.js",
      "crossOrigin": 1
    },
    "ccpBO": {
      "type": "js",
      "src": "https://static.xx.fbcdn.net/rsrc.php/v2/yn/r/8v2_hdH4Nfm.js",
      "crossOrigin": 1
    },
    "sHjT1": {
      "type": "js",
      "src": "https://static.xx.fbcdn.net/rsrc.php/v2iYut3/yh/l/en_GB/bAxpHI-71D1.js",
      "crossOrigin": 1
    },
    "+ClWy": {
      "type": "js",
      "src": "https://static.xx.fbcdn.net/rsrc.php/v2/yH/r/OJIhOkl_3ZX.js",
      "crossOrigin": 1
    },
    "cNca2": {
      "type": "js",
      "src": "https://static.xx.fbcdn.net/rsrc.php/v2/yz/r/y_UrmQfkNB6.js",
      "crossOrigin": 1
    },
    "7+Wvj": {
      "type": "js",
      "src": "https://static.xx.fbcdn.net/rsrc.php/v2iEXa3/yF/l/en_GB/30wOcs9-aw0.js",
      "crossOrigin": 1
    }
  },
  "ixData": {},
  "lid": "6270160135595213544"
}
