{
  "__ar": 1,
  "payload": null,
  "jsmods": {
    "require": [
      [
        "UFICentralUpdates",
        "handleUpdate",
        [],
        [
          19,
          {
            "feedbacktargets": [],
            "comments": [
              {
                "body": {
                  "text": "Don't question the magic of edgerank Eric just enjoy the ride. Looking good John. See you in a few weeks.",
                  "ranges": [
                    {
                      "offset": 37,
                      "length": 4,
                      "entity": {
                        "url": "https://www.facebook.com/ericwahlforss",
                        "id": 607110206,
                        "type": "user"
                      }
                    }
                  ],
                  "aggregatedranges": []
                },
                "isfeatured": false,
                "likecount": 3,
                "hasviewerliked": false,
                "canremove": false,
                "canreport": true,
                "canedit": false,
                "isauthorweakreference": false,
                "istranslatable": false,
                "viewercanlike": true,
                "cancomment": false,
                "spamreplycount": 0,
                "commentshareuri": "/ajax/sharer/?s=69&appid=435066949857522&id=10101668655787801&p%5B0%5D=10101668655787801",
                "id": "508184482641_10101668655787801",
                "fbid": "10101668655787801",
                "legacyid": "10101668655787801",
                "author": "546547924",
                "ftentidentifier": "508184482641",
                "source": 1,
                "highlightcomment": false,
                "timestamp": {
                  "time": 1401690221,
                  "text": "2 June 2014 at 08:23",
                  "verbose": "Monday, 2 June 2014 at 08:23"
                }
              },
              {
                "body": {
                  "text": "How was your weekend, John?",
                  "ranges": [
                    {
                      "offset": 22,
                      "length": 4,
                      "entity": {
                        "url": "https://www.facebook.com/jacoates",
                        "id": 58009281,
                        "type": "user"
                      }
                    }
                  ],
                  "aggregatedranges": []
                },
                "isfeatured": false,
                "likecount": 0,
                "hasviewerliked": false,
                "canremove": false,
                "canreport": true,
                "canedit": false,
                "isauthorweakreference": false,
                "istranslatable": false,
                "viewercanlike": true,
                "cancomment": false,
                "spamreplycount": 0,
                "commentshareuri": "/ajax/sharer/?s=69&appid=435066949857522&id=10101668869948621&p%5B0%5D=10101668869948621",
                "id": "508184482641_10101668869948621",
                "fbid": "10101668869948621",
                "legacyid": "10101668869948621",
                "author": "515643655",
                "ftentidentifier": "508184482641",
                "source": 17,
                "highlightcomment": false,
                "timestamp": {
                  "time": 1401717446,
                  "text": "2 June 2014 at 15:57",
                  "verbose": "Monday, 2 June 2014 at 15:57"
                }
              },
              {
                "body": {
                  "text": "Paul Osman: wrong window?!",
                  "ranges": [],
                  "aggregatedranges": []
                },
                "isfeatured": false,
                "likecount": 0,
                "hasviewerliked": false,
                "canremove": false,
                "canreport": true,
                "canedit": false,
                "isauthorweakreference": false,
                "istranslatable": false,
                "viewercanlike": true,
                "cancomment": false,
                "spamreplycount": 0,
                "commentshareuri": "/ajax/sharer/?s=69&appid=435066949857522&id=10101668936041171&p%5B0%5D=10101668936041171",
                "id": "508184482641_10101668936041171",
                "fbid": "10101668936041171",
                "legacyid": "10101668936041171",
                "author": "100002084191809",
                "ftentidentifier": "508184482641",
                "source": 17,
                "highlightcomment": false,
                "timestamp": {
                  "time": 1401721186,
                  "text": "2 June 2014 at 16:59",
                  "verbose": "Monday, 2 June 2014 at 16:59"
                }
              },
              {
                "body": {
                  "text": ":wq",
                  "ranges": [],
                  "aggregatedranges": []
                },
                "isfeatured": false,
                "likecount": 0,
                "hasviewerliked": false,
                "canremove": false,
                "canreport": true,
                "canedit": false,
                "isauthorweakreference": false,
                "istranslatable": false,
                "viewercanlike": true,
                "cancomment": false,
                "spamreplycount": 0,
                "commentshareuri": "/ajax/sharer/?s=69&appid=435066949857522&id=10101669087318011&p%5B0%5D=10101669087318011",
                "id": "508184482641_10101669087318011",
                "fbid": "10101669087318011",
                "legacyid": "10101669087318011",
                "author": "689412686",
                "ftentidentifier": "508184482641",
                "source": 1,
                "highlightcomment": false,
                "timestamp": {
                  "time": 1401728009,
                  "text": "2 June 2014 at 18:53",
                  "verbose": "Monday, 2 June 2014 at 18:53"
                }
              },
              {
                "body": {
                  "text": "I've let the appropriate people know that this photo should be up on the wall of significant events in SoundCloud's history for 2014.",
                  "ranges": [],
                  "aggregatedranges": []
                },
                "isfeatured": false,
                "likecount": 4,
                "hasviewerliked": false,
                "canremove": false,
                "canreport": true,
                "canedit": false,
                "isauthorweakreference": false,
                "istranslatable": false,
                "viewercanlike": true,
                "cancomment": false,
                "spamreplycount": 0,
                "commentshareuri": "/ajax/sharer/?s=69&appid=435066949857522&id=10101672490123761&p%5B0%5D=10101672490123761",
                "id": "508184482641_10101672490123761",
                "fbid": "10101672490123761",
                "legacyid": "10101672490123761",
                "author": "689412686",
                "ftentidentifier": "508184482641",
                "source": 1,
                "highlightcomment": false,
                "timestamp": {
                  "time": 1401903619,
                  "text": "4 June 2014 at 19:40",
                  "verbose": "Wednesday, 4 June 2014 at 19:40"
                }
              },
              {
                "body": {
                  "text": "Fronx: It's never the wrong window if this photo is in it.",
                  "ranges": [],
                  "aggregatedranges": []
                },
                "isfeatured": false,
                "likecount": 1,
                "hasviewerliked": false,
                "canremove": false,
                "canreport": true,
                "canedit": false,
                "isauthorweakreference": false,
                "istranslatable": false,
                "viewercanlike": true,
                "cancomment": false,
                "spamreplycount": 0,
                "commentshareuri": "/ajax/sharer/?s=69&appid=435066949857522&id=10101672496266451&p%5B0%5D=10101672496266451",
                "id": "508184482641_10101672496266451",
                "fbid": "10101672496266451",
                "legacyid": "10101672496266451",
                "author": "515643655",
                "ftentidentifier": "508184482641",
                "source": 2,
                "highlightcomment": false,
                "timestamp": {
                  "time": 1401903986,
                  "text": "4 June 2014 at 19:46",
                  "verbose": "Wednesday, 4 June 2014 at 19:46"
                }
              },
              {
                "body": {
                  "text": "Edward J Coombe Jami Welch --> Oliver Hookins has your back.",
                  "ranges": [
                    {
                      "offset": 0,
                      "length": 15,
                      "entity": {
                        "url": "https://www.facebook.com/ejcoombe",
                        "id": 508503179,
                        "type": "user"
                      }
                    },
                    {
                      "offset": 16,
                      "length": 10,
                      "entity": {
                        "url": "https://www.facebook.com/welchjames",
                        "id": 100000538166201,
                        "type": "user"
                      }
                    },
                    {
                      "offset": 31,
                      "length": 14,
                      "entity": {
                        "url": "https://www.facebook.com/oliver.hookins",
                        "id": 689412686,
                        "type": "user"
                      }
                    }
                  ],
                  "aggregatedranges": []
                },
                "isfeatured": false,
                "likecount": 0,
                "hasviewerliked": false,
                "canremove": false,
                "canreport": true,
                "canedit": false,
                "isauthorweakreference": false,
                "istranslatable": false,
                "viewercanlike": true,
                "cancomment": false,
                "spamreplycount": 0,
                "commentshareuri": "/ajax/sharer/?s=69&appid=435066949857522&id=10101672497109761&p%5B0%5D=10101672497109761",
                "id": "508184482641_10101672497109761",
                "fbid": "10101672497109761",
                "legacyid": "10101672497109761",
                "author": "58009281",
                "ftentidentifier": "508184482641",
                "source": 17,
                "highlightcomment": false,
                "timestamp": {
                  "time": 1401904038,
                  "text": "4 June 2014 at 19:47",
                  "verbose": "Wednesday, 4 June 2014 at 19:47"
                }
              },
              {
                "body": {
                  "text": "Oliver Hookins John Coates - I placed a copy on the historical events wall display, but there was a copy already there!",
                  "ranges": [
                    {
                      "offset": 0,
                      "length": 14,
                      "entity": {
                        "url": "https://www.facebook.com/oliver.hookins",
                        "id": 689412686,
                        "type": "user"
                      }
                    },
                    {
                      "offset": 15,
                      "length": 11,
                      "entity": {
                        "url": "https://www.facebook.com/jacoates",
                        "id": 58009281,
                        "type": "user"
                      }
                    }
                  ],
                  "aggregatedranges": []
                },
                "isfeatured": false,
                "likecount": 1,
                "hasviewerliked": false,
                "canremove": false,
                "canreport": true,
                "canedit": false,
                "isauthorweakreference": false,
                "istranslatable": false,
                "viewercanlike": true,
                "cancomment": false,
                "spamreplycount": 0,
                "commentshareuri": "/ajax/sharer/?s=69&appid=435066949857522&id=10101672504804341&p%5B0%5D=10101672504804341",
                "id": "508184482641_10101672504804341",
                "fbid": "10101672504804341",
                "legacyid": "10101672504804341",
                "author": "100000538166201",
                "ftentidentifier": "508184482641",
                "source": 1,
                "highlightcomment": false,
                "timestamp": {
                  "time": 1401904227,
                  "text": "4 June 2014 at 19:50",
                  "verbose": "Wednesday, 4 June 2014 at 19:50"
                }
              },
              {
                "body": {
                  "text": "Jami it's only fair that we also print the comments out in full too.",
                  "ranges": [
                    {
                      "offset": 0,
                      "length": 4,
                      "entity": {
                        "url": "https://www.facebook.com/welchjames",
                        "id": 100000538166201,
                        "type": "user"
                      }
                    }
                  ],
                  "aggregatedranges": []
                },
                "isfeatured": false,
                "likecount": 3,
                "hasviewerliked": false,
                "canremove": false,
                "canreport": true,
                "canedit": false,
                "isauthorweakreference": false,
                "istranslatable": false,
                "viewercanlike": true,
                "cancomment": false,
                "spamreplycount": 0,
                "commentshareuri": "/ajax/sharer/?s=69&appid=435066949857522&id=10101672505747451&p%5B0%5D=10101672505747451",
                "id": "508184482641_10101672505747451",
                "fbid": "10101672505747451",
                "legacyid": "10101672505747451",
                "author": "689412686",
                "ftentidentifier": "508184482641",
                "source": 17,
                "highlightcomment": false,
                "timestamp": {
                  "time": 1401904284,
                  "text": "4 June 2014 at 19:51",
                  "verbose": "Wednesday, 4 June 2014 at 19:51"
                }
              },
              {
                "body": {
                  "text": "i just went on the factory tour and there's a special booth room for comment-making on this photo",
                  "ranges": [],
                  "aggregatedranges": []
                },
                "isfeatured": false,
                "likecount": 7,
                "hasviewerliked": false,
                "canremove": false,
                "canreport": true,
                "canedit": false,
                "isauthorweakreference": false,
                "istranslatable": false,
                "viewercanlike": true,
                "cancomment": false,
                "spamreplycount": 0,
                "commentshareuri": "/ajax/sharer/?s=69&appid=435066949857522&id=10101672629125201&p%5B0%5D=10101672629125201",
                "id": "508184482641_10101672629125201",
                "fbid": "10101672629125201",
                "legacyid": "10101672629125201",
                "author": "821488",
                "ftentidentifier": "508184482641",
                "source": 1,
                "highlightcomment": false,
                "timestamp": {
                  "time": 1401910144,
                  "text": "4 June 2014 at 21:29",
                  "verbose": "Wednesday, 4 June 2014 at 21:29"
                }
              }
            ],
            "profiles": [
              {
                "id": "546547924",
                "name": "Jon Schmidt",
                "firstName": "Jon",
                "vanity": "jonathanmschmidt",
                "thumbSrc": "https://scontent.ftxl1-1.fna.fbcdn.net/hprofile-xpt1/v/t1.0-1/p64x64/12079316_10154806002837925_3726767938778979195_n.jpg?oh=0e514d1c6b976e0bcdc67f3e42541c07&oe=5775F991",
                "uri": "https://www.facebook.com/jonathanmschmidt?fref=ufi",
                "gender": 2,
                "i18nGender": 16777216,
                "type": "user",
                "is_friend": false
              },
              {
                "id": "515643655",
                "name": "Paul Osman",
                "firstName": "Paul",
                "vanity": "paulosman",
                "thumbSrc": "https://scontent.ftxl1-1.fna.fbcdn.net/hprofile-xtp1/v/t1.0-1/p64x64/12189103_10153751746673656_2432118809107327150_n.jpg?oh=b71c091b4b0ab8279d06b0897288187e&oe=5776FCC3",
                "uri": "https://www.facebook.com/paulosman?fref=ufi",
                "gender": 2,
                "i18nGender": 16777216,
                "type": "user",
                "is_friend": false
              },
              {
                "id": "100002084191809",
                "name": "Fronx Wurmus",
                "firstName": "Fronx",
                "vanity": "fronx.wurmus",
                "thumbSrc": "https://scontent.ftxl1-1.fna.fbcdn.net/hprofile-xfp1/v/t1.0-1/p64x64/10603580_959281544151310_5296240726314978519_n.jpg?oh=f392cdcdf9f1e7d5b42c2875c0202b9e&oe=57BC34A1",
                "uri": "https://www.facebook.com/fronx.wurmus?fref=ufi",
                "gender": 6,
                "i18nGender": 50331648,
                "type": "user",
                "is_friend": false
              },
              {
                "id": "689412686",
                "name": "Oliver Hookins",
                "firstName": "Oliver",
                "vanity": "oliver.hookins",
                "thumbSrc": "https://scontent.ftxl1-1.fna.fbcdn.net/hprofile-xtf1/v/t1.0-1/p64x64/1930350_10153230195892687_9007624726573013478_n.jpg?oh=93b2000391c4f2105fa76d9b6688810a&oe=578816CB",
                "uri": "https://www.facebook.com/oliver.hookins?fref=ufi",
                "gender": 2,
                "i18nGender": 16777216,
                "type": "user",
                "is_friend": false
              },
              {
                "id": "58009281",
                "name": "John Coates",
                "firstName": "John",
                "vanity": "jacoates",
                "thumbSrc": "https://scontent.ftxl1-1.fna.fbcdn.net/hprofile-xlf1/v/t1.0-1/p64x64/12341463_10102478223412791_4716757936331031777_n.jpg?oh=86b4d8c659a8fe8bb7db5b702ff5bd0f&oe=5776C08D",
                "uri": "https://www.facebook.com/jacoates?fref=ufi",
                "gender": 2,
                "i18nGender": 16777216,
                "type": "friend",
                "is_friend": true
              },
              {
                "id": "100000538166201",
                "name": "Jami Welch",
                "firstName": "Jami",
                "vanity": "welchjames",
                "thumbSrc": "https://scontent.ftxl1-1.fna.fbcdn.net/hprofile-xat1/v/t1.0-1/p64x64/12141670_1120647327963195_3030662252651092087_n.jpg?oh=95bd33703721b98964ed0ddd561f5f69&oe=577C625E",
                "uri": "https://www.facebook.com/welchjames?fref=ufi",
                "gender": 7,
                "i18nGender": 50331648,
                "type": "friend",
                "is_friend": true
              },
              {
                "id": "821488",
                "name": "Eileen Tang",
                "firstName": "Eileen",
                "vanity": "eileentang",
                "thumbSrc": "https://scontent.ftxl1-1.fna.fbcdn.net/hprofile-xat1/v/t1.0-1/p64x64/12032033_10104333322413949_4065232509477088740_n.jpg?oh=a7ec1696de064b347a3b018c06088210&oe=57BF2DA4",
                "uri": "https://www.facebook.com/eileentang?fref=ufi",
                "gender": 7,
                "i18nGender": 50331648,
                "type": "user",
                "is_friend": false
              }
            ],
            "actions": [],
            "commentlists": {
              "comments": {
                "508184482641": {
                  "chronological": {
                    "range": {
                      "offset": 150,
                      "length": 10
                    },
                    "values": [
                      "508184482641_10101668655787801",
                      "508184482641_10101668869948621",
                      "508184482641_10101668936041171",
                      "508184482641_10101669087318011",
                      "508184482641_10101672490123761",
                      "508184482641_10101672496266451",
                      "508184482641_10101672497109761",
                      "508184482641_10101672504804341",
                      "508184482641_10101672505747451",
                      "508184482641_10101672629125201"
                    ],
                    "count": 571
                  }
                }
              },
              "replies": {
                "508184482641_10101668655787801": {
                  "range": {
                    "offset": 0,
                    "length": 0
                  },
                  "values": [],
                  "count": 0,
                  "ftentidentifier": 508184482641,
                  "containerorderingmode": "chronological"
                },
                "508184482641_10101668869948621": {
                  "range": {
                    "offset": 0,
                    "length": 0
                  },
                  "values": [],
                  "count": 0,
                  "ftentidentifier": 508184482641,
                  "containerorderingmode": "chronological"
                },
                "508184482641_10101668936041171": {
                  "range": {
                    "offset": 0,
                    "length": 0
                  },
                  "values": [],
                  "count": 0,
                  "ftentidentifier": 508184482641,
                  "containerorderingmode": "chronological"
                },
                "508184482641_10101669087318011": {
                  "range": {
                    "offset": 0,
                    "length": 0
                  },
                  "values": [],
                  "count": 0,
                  "ftentidentifier": 508184482641,
                  "containerorderingmode": "chronological"
                },
                "508184482641_10101672490123761": {
                  "range": {
                    "offset": 0,
                    "length": 0
                  },
                  "values": [],
                  "count": 0,
                  "ftentidentifier": 508184482641,
                  "containerorderingmode": "chronological"
                },
                "508184482641_10101672496266451": {
                  "range": {
                    "offset": 0,
                    "length": 0
                  },
                  "values": [],
                  "count": 0,
                  "ftentidentifier": 508184482641,
                  "containerorderingmode": "chronological"
                },
                "508184482641_10101672497109761": {
                  "range": {
                    "offset": 0,
                    "length": 0
                  },
                  "values": [],
                  "count": 0,
                  "ftentidentifier": 508184482641,
                  "containerorderingmode": "chronological"
                },
                "508184482641_10101672504804341": {
                  "range": {
                    "offset": 0,
                    "length": 0
                  },
                  "values": [],
                  "count": 0,
                  "ftentidentifier": 508184482641,
                  "containerorderingmode": "chronological"
                },
                "508184482641_10101672505747451": {
                  "range": {
                    "offset": 0,
                    "length": 0
                  },
                  "values": [],
                  "count": 0,
                  "ftentidentifier": 508184482641,
                  "containerorderingmode": "chronological"
                },
                "508184482641_10101672629125201": {
                  "range": {
                    "offset": 0,
                    "length": 0
                  },
                  "values": [],
                  "count": 0,
                  "ftentidentifier": 508184482641,
                  "containerorderingmode": "chronological"
                }
              }
            },
            "featuredcommentlists": {
              "comments": null,
              "replies": null
            },
            "servertime": 1459885398
          }
        ],
        []
      ]
    ]
  },
  "css": [
    "ChMB+"
  ],
  "js": [
    "/NqAA",
    "ThKmv",
    "7+Wvj",
    "RVoyp"
  ],
  "bootloadable": {
    "AsyncSignal": {
      "resources": [
        "/NqAA",
        "ChMB+"
      ],
      "module": 1
    },
    "XLinkshimLogController": {
      "resources": [
        "/NqAA",
        "ThKmv",
        "oeUXN"
      ],
      "module": 1
    },
    "ExceptionDialog": {
      "resources": [
        "/NqAA",
        "vjV9S",
        "ChMB+",
        "ThKmv",
        "GHhcl",
        "RVoyp",
        "xRvqJ",
        "M99oK",
        "nyijU",
        "xxecq"
      ],
      "module": 1
    },
    "React": {
      "resources": [
        "RVoyp",
        "ThKmv",
        "/NqAA",
        "ChMB+"
      ],
      "module": 1
    },
    "AsyncDOM": {
      "resources": [
        "/NqAA",
        "ChMB+",
        "kCdR4"
      ],
      "module": 1
    },
    "ConfirmationDialog": {
      "resources": [
        "/NqAA",
        "ChMB+",
        "oE4Do"
      ],
      "module": 1
    },
    "Dialog": {
      "resources": [
        "/NqAA",
        "ThKmv",
        "ChMB+",
        "vjV9S",
        "nyijU",
        "PnFXr"
      ],
      "module": 1
    },
    "QuickSandSolver": {
      "resources": [
        "/NqAA",
        "ChMB+",
        "PNiUp",
        "ccpBO",
        "ThKmv",
        "sHjT1",
        "+ClWy"
      ],
      "module": 1
    },
    "ErrorSignal": {
      "resources": [
        "/NqAA",
        "ChMB+",
        "cNca2"
      ],
      "module": 1
    },
    "ReactDOM": {
      "resources": [
        "RVoyp",
        "ThKmv",
        "/NqAA",
        "ChMB+"
      ],
      "module": 1
    }
  },
  "resource_map": {
    "/NqAA": {
      "type": "js",
      "src": "https://static.xx.fbcdn.net/rsrc.php/v2iWxT3/yx/l/en_GB/HROIdTujVmr.js",
      "crossOrigin": 1
    },
    "ChMB+": {
      "type": "css",
      "src": "https://static.xx.fbcdn.net/rsrc.php/v2/yx/r/k3Q2XVxSzbX.css",
      "permanent": 1,
      "crossOrigin": 1
    },
    "ThKmv": {
      "type": "js",
      "src": "https://static.xx.fbcdn.net/rsrc.php/v2icMq3/yq/l/en_GB/aDAQ5kMH0Pn.js",
      "crossOrigin": 1
    },
    "oeUXN": {
      "type": "js",
      "src": "https://static.xx.fbcdn.net/rsrc.php/v2/yZ/r/aBvqchyj98N.js",
      "crossOrigin": 1
    },
    "vjV9S": {
      "type": "js",
      "src": "https://static.xx.fbcdn.net/rsrc.php/v2iXqO3/yy/l/en_GB/gr9cOlHfR7a.js",
      "crossOrigin": 1
    },
    "GHhcl": {
      "type": "css",
      "src": "https://static.xx.fbcdn.net/rsrc.php/v2/yD/r/M1T65RA6tXh.css",
      "permanent": 1,
      "crossOrigin": 1
    },
    "RVoyp": {
      "type": "js",
      "src": "https://static.xx.fbcdn.net/rsrc.php/v2iwdk3/yW/l/en_GB/1knLCNg5RDa.js",
      "crossOrigin": 1
    },
    "xRvqJ": {
      "type": "js",
      "src": "https://static.xx.fbcdn.net/rsrc.php/v2ixjD3/yL/l/en_GB/G9SciDaoLgv.js",
      "crossOrigin": 1
    },
    "M99oK": {
      "type": "js",
      "src": "https://static.xx.fbcdn.net/rsrc.php/v2i6Fo3/yT/l/en_GB/irADvQCTTxL.js",
      "crossOrigin": 1
    },
    "nyijU": {
      "type": "css",
      "src": "https://static.xx.fbcdn.net/rsrc.php/v2/yi/r/nGIJR7qmC-t.css",
      "permanent": 1,
      "crossOrigin": 1
    },
    "xxecq": {
      "type": "js",
      "src": "https://static.xx.fbcdn.net/rsrc.php/v2iEvA3/y5/l/en_GB/vZhgfyaOfr4.js",
      "crossOrigin": 1
    },
    "kCdR4": {
      "type": "js",
      "src": "https://static.xx.fbcdn.net/rsrc.php/v2/yn/r/JzB2tsQVw-3.js",
      "crossOrigin": 1
    },
    "oE4Do": {
      "type": "js",
      "src": "https://static.xx.fbcdn.net/rsrc.php/v2/yq/r/g65Ifm-JIn6.js",
      "crossOrigin": 1
    },
    "PnFXr": {
      "type": "js",
      "src": "https://static.xx.fbcdn.net/rsrc.php/v2i55M3/yA/l/en_GB/W1TltFpUoyK.js",
      "crossOrigin": 1
    },
    "PNiUp": {
      "type": "js",
      "src": "https://static.xx.fbcdn.net/rsrc.php/v2/ys/r/m5QDGyZX8QU.js",
      "crossOrigin": 1
    },
    "ccpBO": {
      "type": "js",
      "src": "https://static.xx.fbcdn.net/rsrc.php/v2/yn/r/8v2_hdH4Nfm.js",
      "crossOrigin": 1
    },
    "sHjT1": {
      "type": "js",
      "src": "https://static.xx.fbcdn.net/rsrc.php/v2iYut3/yh/l/en_GB/bAxpHI-71D1.js",
      "crossOrigin": 1
    },
    "+ClWy": {
      "type": "js",
      "src": "https://static.xx.fbcdn.net/rsrc.php/v2/yH/r/OJIhOkl_3ZX.js",
      "crossOrigin": 1
    },
    "cNca2": {
      "type": "js",
      "src": "https://static.xx.fbcdn.net/rsrc.php/v2/yz/r/y_UrmQfkNB6.js",
      "crossOrigin": 1
    },
    "7+Wvj": {
      "type": "js",
      "src": "https://static.xx.fbcdn.net/rsrc.php/v2iEXa3/yF/l/en_GB/30wOcs9-aw0.js",
      "crossOrigin": 1
    }
  },
  "ixData": {},
  "lid": "6270160041544014267"
}
