{
  "__ar": 1,
  "payload": null,
  "jsmods": {
    "markup": [
      [
        "__markup_846a1dcb_n_0",
        {
          "__html": "<div class=\"mvs\"><a class=\"_2rn3 _4-eo\" href=\"https://www.facebook.com/photo.php?fbid=10153371484997687&amp;set=p.10153371484997687&amp;type=3\" rel=\"theater\" ajaxify=\"https://www.facebook.com/photo.php?fbid=10153371484997687&amp;set=p.10153371484997687&amp;type=3&amp;size=960%2C540&amp;source=24&amp;player_origin=feedback\"><div class=\"uiScaledImageContainer _4-ep\" style=\"width:260px;height:145px;\"><img class=\"scaledImageFitWidth img\" src=\"https://scontent.ftxl1-1.fna.fbcdn.net/hphotos-xlp1/v/t1.0-0/q82/s526x296/12512221_10153371484997687_4587032124563969694_n.jpg?oh=78e99276c0bcf9bda9e84736d6a60765&amp;oe=5779D00A\" alt=\"Oliver Hookins&#039;s photo.\" width=\"260\" height=\"146\" /></div></a></div>"
        },
        1
      ],
      [
        "__markup_a0d94362_n_0",
        {
          "__html": "<div class=\"uiScaledImageContainer\" style=\"width:120px;height:67px;\"><img class=\"scaledImageFitWidth img\" src=\"https://scontent.ftxl1-1.fna.fbcdn.net/hphotos-xlp1/v/t1.0-0/q82/s240x240/12512221_10153371484997687_4587032124563969694_n.jpg?oh=c7b1a6c129db86ecfd5a5b2544cb85ea&amp;oe=577F900D\" alt=\"Oliver Hookins&#039;s photo.\" width=\"120\" height=\"68\" /></div>"
        },
        1
      ]
    ],
    "require": [
      [
        "UFICentralUpdates",
        "handleUpdate",
        [
          "__markup_846a1dcb_n_0",
          "__markup_a0d94362_n_0"
        ],
        [
          19,
          {
            "feedbacktargets": [],
            "comments": [
              {
                "body": {
                  "text": "praise be!",
                  "ranges": [],
                  "aggregatedranges": []
                },
                "isfeatured": false,
                "likecount": 2,
                "hasviewerliked": false,
                "canremove": false,
                "canreport": true,
                "canedit": false,
                "isauthorweakreference": false,
                "istranslatable": false,
                "viewercanlike": true,
                "cancomment": false,
                "spamreplycount": 0,
                "commentshareuri": "/ajax/sharer/?s=69&appid=435066949857522&id=10102617665100531&p%5B0%5D=10102617665100531",
                "id": "508184482641_10102617665100531",
                "fbid": "10102617665100531",
                "legacyid": "10102617665100531",
                "author": "7406979",
                "ftentidentifier": "508184482641",
                "source": 17,
                "highlightcomment": false,
                "timestamp": {
                  "time": 1458864122,
                  "text": "25 March at 01:02",
                  "verbose": "Friday, 25 March 2016 at 01:02"
                }
              },
              {
                "body": {
                  "text": "have a great easter john",
                  "ranges": [],
                  "aggregatedranges": []
                },
                "isfeatured": false,
                "likecount": 6,
                "hasviewerliked": false,
                "canremove": false,
                "canreport": true,
                "canedit": false,
                "isauthorweakreference": false,
                "istranslatable": false,
                "viewercanlike": true,
                "cancomment": false,
                "spamreplycount": 0,
                "commentshareuri": "/ajax/sharer/?s=69&appid=435066949857522&id=10102620280219811&p%5B0%5D=10102620280219811",
                "id": "508184482641_10102620280219811",
                "fbid": "10102620280219811",
                "legacyid": "10102620280219811",
                "author": "507692735",
                "ftentidentifier": "508184482641",
                "source": 3,
                "highlightcomment": false,
                "timestamp": {
                  "time": 1459006894,
                  "text": "26 March at 16:41",
                  "verbose": "Saturday, 26 March 2016 at 16:41"
                }
              },
              {
                "body": {
                  "text": "Yes happy easter everyone! Are you up to anything this weekend John?",
                  "ranges": [],
                  "aggregatedranges": []
                },
                "isfeatured": false,
                "likecount": 3,
                "hasviewerliked": false,
                "canremove": false,
                "canreport": true,
                "canedit": false,
                "isauthorweakreference": false,
                "istranslatable": false,
                "viewercanlike": true,
                "cancomment": false,
                "spamreplycount": 0,
                "commentshareuri": "/ajax/sharer/?s=69&appid=435066949857522&id=10102620286347531&p%5B0%5D=10102620286347531",
                "id": "508184482641_10102620286347531",
                "fbid": "10102620286347531",
                "legacyid": "10102620286347531",
                "author": "23911310",
                "ftentidentifier": "508184482641",
                "source": 3,
                "highlightcomment": false,
                "timestamp": {
                  "time": 1459007229,
                  "text": "26 March at 16:47",
                  "verbose": "Saturday, 26 March 2016 at 16:47"
                }
              },
              {
                "body": {
                  "text": "I painted eggs yesterday and it was surprisingly awesome.",
                  "ranges": [],
                  "aggregatedranges": []
                },
                "isfeatured": false,
                "likecount": 6,
                "hasviewerliked": false,
                "canremove": false,
                "canreport": true,
                "canedit": false,
                "isauthorweakreference": false,
                "istranslatable": false,
                "viewercanlike": true,
                "cancomment": false,
                "spamreplycount": 0,
                "commentshareuri": "/ajax/sharer/?s=69&appid=435066949857522&id=10102620290299611&p%5B0%5D=10102620290299611",
                "id": "508184482641_10102620290299611",
                "fbid": "10102620290299611",
                "legacyid": "10102620290299611",
                "author": "689412686",
                "ftentidentifier": "508184482641",
                "source": 17,
                "highlightcomment": false,
                "timestamp": {
                  "time": 1459007446,
                  "text": "26 March at 16:50",
                  "verbose": "Saturday, 26 March 2016 at 16:50"
                }
              },
              {
                "body": {
                  "text": "Engage in random acts of egg painting.",
                  "ranges": [],
                  "aggregatedranges": []
                },
                "isfeatured": false,
                "likecount": 2,
                "hasviewerliked": false,
                "canremove": false,
                "canreport": true,
                "canedit": false,
                "isauthorweakreference": false,
                "istranslatable": false,
                "viewercanlike": true,
                "cancomment": false,
                "spamreplycount": 0,
                "commentshareuri": "/ajax/sharer/?s=69&appid=435066949857522&id=10102620631994851&p%5B0%5D=10102620631994851",
                "id": "508184482641_10102620631994851",
                "fbid": "10102620631994851",
                "legacyid": "10102620631994851",
                "author": "515643655",
                "ftentidentifier": "508184482641",
                "source": 3,
                "highlightcomment": false,
                "timestamp": {
                  "time": 1459020830,
                  "text": "26 March at 20:33",
                  "verbose": "Saturday, 26 March 2016 at 20:33"
                }
              },
              {
                "body": {
                  "text": "Easter fire going on here in east Germany. Would recommend >>>>",
                  "ranges": [],
                  "aggregatedranges": []
                },
                "isfeatured": false,
                "likecount": 3,
                "hasviewerliked": false,
                "canremove": false,
                "canreport": true,
                "canedit": false,
                "isauthorweakreference": false,
                "istranslatable": false,
                "viewercanlike": true,
                "cancomment": false,
                "spamreplycount": 0,
                "commentshareuri": "/ajax/sharer/?s=69&appid=435066949857522&id=10102620682568501&p%5B0%5D=10102620682568501",
                "id": "508184482641_10102620682568501",
                "fbid": "10102620682568501",
                "legacyid": "10102620682568501",
                "author": "620656534",
                "ftentidentifier": "508184482641",
                "source": 3,
                "highlightcomment": false,
                "timestamp": {
                  "time": 1459023321,
                  "text": "26 March at 21:15",
                  "verbose": "Saturday, 26 March 2016 at 21:15"
                }
              },
              {
                "body": {
                  "text": "Paul I eggaged in random acts.",
                  "ranges": [
                    {
                      "offset": 0,
                      "length": 4,
                      "entity": {
                        "url": "https://www.facebook.com/paulosman",
                        "id": 515643655,
                        "type": "user"
                      }
                    }
                  ],
                  "aggregatedranges": []
                },
                "isfeatured": false,
                "likecount": 3,
                "hasviewerliked": false,
                "canremove": false,
                "canreport": true,
                "canedit": false,
                "isauthorweakreference": false,
                "istranslatable": false,
                "viewercanlike": true,
                "cancomment": false,
                "spamreplycount": 0,
                "commentshareuri": "/ajax/sharer/?s=69&appid=435066949857522&id=10102620805177791&p%5B0%5D=10102620805177791",
                "id": "508184482641_10102620805177791",
                "fbid": "10102620805177791",
                "legacyid": "10102620805177791",
                "author": "689412686",
                "ftentidentifier": "508184482641",
                "source": 17,
                "highlightcomment": false,
                "timestamp": {
                  "time": 1459029324,
                  "text": "26 March at 22:55",
                  "verbose": "Saturday, 26 March 2016 at 22:55"
                }
              },
              {
                "body": {
                  "text": "Oliver: \\o/ !!!",
                  "ranges": [
                    {
                      "offset": 0,
                      "length": 6,
                      "entity": {
                        "url": "https://www.facebook.com/oliver.hookins",
                        "id": 689412686,
                        "type": "user"
                      }
                    }
                  ],
                  "aggregatedranges": []
                },
                "isfeatured": false,
                "likecount": 0,
                "hasviewerliked": false,
                "canremove": false,
                "canreport": true,
                "canedit": false,
                "isauthorweakreference": false,
                "istranslatable": false,
                "viewercanlike": true,
                "cancomment": false,
                "spamreplycount": 0,
                "commentshareuri": "/ajax/sharer/?s=69&appid=435066949857522&id=10102620824903261&p%5B0%5D=10102620824903261",
                "id": "508184482641_10102620824903261",
                "fbid": "10102620824903261",
                "legacyid": "10102620824903261",
                "author": "515643655",
                "ftentidentifier": "508184482641",
                "source": 3,
                "highlightcomment": false,
                "timestamp": {
                  "time": 1459030208,
                  "text": "26 March at 23:10",
                  "verbose": "Saturday, 26 March 2016 at 23:10"
                }
              },
              {
                "body": {
                  "text": "I can't count how many times this picture has shown up in my timeline already.",
                  "ranges": [],
                  "aggregatedranges": []
                },
                "isfeatured": false,
                "likecount": 0,
                "hasviewerliked": false,
                "canremove": false,
                "canreport": true,
                "canedit": false,
                "isauthorweakreference": false,
                "istranslatable": false,
                "viewercanlike": true,
                "cancomment": false,
                "spamreplycount": 0,
                "commentshareuri": "/ajax/sharer/?s=69&appid=435066949857522&id=10102622186260091&p%5B0%5D=10102622186260091",
                "id": "508184482641_10102622186260091",
                "fbid": "10102622186260091",
                "legacyid": "10102622186260091",
                "author": "508814106",
                "ftentidentifier": "508184482641",
                "source": 1,
                "highlightcomment": false,
                "timestamp": {
                  "time": 1459099016,
                  "text": "27 March at 19:16",
                  "verbose": "Sunday, 27 March 2016 at 19:16"
                }
              },
              {
                "body": {
                  "text": "Happy easter from robo bunny",
                  "ranges": [],
                  "aggregatedranges": []
                },
                "isfeatured": false,
                "likecount": 1,
                "hasviewerliked": false,
                "canremove": false,
                "canreport": true,
                "canedit": false,
                "isauthorweakreference": false,
                "istranslatable": false,
                "viewercanlike": true,
                "cancomment": false,
                "spamreplycount": 0,
                "commentshareuri": "/ajax/sharer/?s=69&appid=435066949857522&id=10102622190661271&p%5B0%5D=10102622190661271",
                "id": "508184482641_10102622190661271",
                "fbid": "10102622190661271",
                "legacyid": "10102622190661271",
                "author": "689412686",
                "ftentidentifier": "508184482641",
                "source": 17,
                "highlightcomment": false,
                "timestamp": {
                  "time": 1459099233,
                  "text": "27 March at 19:20",
                  "verbose": "Sunday, 27 March 2016 at 19:20"
                },
                "photo_comment": {
                  "fbid": "10153371484997687",
                  "markup": {
                    "__m": "__markup_846a1dcb_n_0"
                  },
                  "markupPreview": {
                    "__m": "__markup_a0d94362_n_0"
                  }
                }
              }
            ],
            "profiles": [
              {
                "id": "7406979",
                "name": "Adam Greis",
                "firstName": "Adam",
                "vanity": "adam.greis",
                "thumbSrc": "https://scontent.ftxl1-1.fna.fbcdn.net/hprofile-xal1/v/t1.0-1/p64x64/10391398_10101182166415895_7968193692302777229_n.jpg?oh=c6105b8901dd075e1d60b38cfa24d502&oe=5786DC6B",
                "uri": "https://www.facebook.com/adam.greis?fref=ufi",
                "gender": 2,
                "i18nGender": 16777216,
                "type": "user",
                "is_friend": false
              },
              {
                "id": "507692735",
                "name": "Jessica Shea",
                "firstName": "Jessica",
                "vanity": "jess.shea",
                "thumbSrc": "https://scontent.ftxl1-1.fna.fbcdn.net/hprofile-xfa1/v/t1.0-1/p64x64/12931250_10153641885157736_4724989224742271164_n.jpg?oh=4d6f88e57a1d7b1527c14e032d268bd7&oe=577898D1",
                "uri": "https://www.facebook.com/jess.shea?fref=ufi",
                "gender": 1,
                "i18nGender": 33554432,
                "type": "user",
                "is_friend": false
              },
              {
                "id": "23911310",
                "name": "Cole Mercer",
                "firstName": "Cole",
                "vanity": "cmercer1",
                "thumbSrc": "https://scontent.ftxl1-1.fna.fbcdn.net/hprofile-xpf1/v/t1.0-1/p64x64/10881704_10103110093554620_8303054274959248956_n.jpg?oh=722425a4aa000418fd5bc4017d48f4ca&oe=578DFE51",
                "uri": "https://www.facebook.com/cmercer1?fref=ufi",
                "gender": 2,
                "i18nGender": 16777216,
                "type": "friend",
                "is_friend": true
              },
              {
                "id": "689412686",
                "name": "Oliver Hookins",
                "firstName": "Oliver",
                "vanity": "oliver.hookins",
                "thumbSrc": "https://scontent.ftxl1-1.fna.fbcdn.net/hprofile-xtf1/v/t1.0-1/p64x64/1930350_10153230195892687_9007624726573013478_n.jpg?oh=93b2000391c4f2105fa76d9b6688810a&oe=578816CB",
                "uri": "https://www.facebook.com/oliver.hookins?fref=ufi",
                "gender": 2,
                "i18nGender": 16777216,
                "type": "user",
                "is_friend": false
              },
              {
                "id": "515643655",
                "name": "Paul Osman",
                "firstName": "Paul",
                "vanity": "paulosman",
                "thumbSrc": "https://scontent.ftxl1-1.fna.fbcdn.net/hprofile-xtp1/v/t1.0-1/p64x64/12189103_10153751746673656_2432118809107327150_n.jpg?oh=b71c091b4b0ab8279d06b0897288187e&oe=5776FCC3",
                "uri": "https://www.facebook.com/paulosman?fref=ufi",
                "gender": 2,
                "i18nGender": 16777216,
                "type": "user",
                "is_friend": false
              },
              {
                "id": "620656534",
                "name": "Vincent Garrigues",
                "firstName": "Vincent",
                "vanity": "vincent.garrigues",
                "thumbSrc": "https://scontent.ftxl1-1.fna.fbcdn.net/hprofile-xat1/v/t1.0-1/p64x64/12105800_10153887761201535_8288001405451785888_n.jpg?oh=3e32c830b67d7f91c75a352466b4fe37&oe=578B3E61",
                "uri": "https://www.facebook.com/vincent.garrigues?fref=ufi",
                "gender": 2,
                "i18nGender": 16777216,
                "type": "friend",
                "is_friend": true
              },
              {
                "id": "508814106",
                "name": "Julius Volz",
                "firstName": "Julius",
                "vanity": "julius.volz",
                "thumbSrc": "https://scontent.ftxl1-1.fna.fbcdn.net/hprofile-xap1/v/t1.0-1/p64x64/11960270_10153241323484107_5704399667893621037_n.jpg?oh=c66128e617bbd5d06ccde4a18fdf92f9&oe=578D448C",
                "uri": "https://www.facebook.com/julius.volz?fref=ufi",
                "gender": 2,
                "i18nGender": 16777216,
                "type": "user",
                "is_friend": false
              }
            ],
            "actions": [],
            "commentlists": {
              "comments": {
                "508184482641": {
                  "chronological": {
                    "range": {
                      "offset": 510,
                      "length": 10
                    },
                    "values": [
                      "508184482641_10102617665100531",
                      "508184482641_10102620280219811",
                      "508184482641_10102620286347531",
                      "508184482641_10102620290299611",
                      "508184482641_10102620631994851",
                      "508184482641_10102620682568501",
                      "508184482641_10102620805177791",
                      "508184482641_10102620824903261",
                      "508184482641_10102622186260091",
                      "508184482641_10102622190661271"
                    ],
                    "count": 571
                  }
                }
              },
              "replies": {
                "508184482641_10102617665100531": {
                  "range": {
                    "offset": 0,
                    "length": 0
                  },
                  "values": [],
                  "count": 0,
                  "ftentidentifier": 508184482641,
                  "containerorderingmode": "chronological"
                },
                "508184482641_10102620280219811": {
                  "range": {
                    "offset": 0,
                    "length": 0
                  },
                  "values": [],
                  "count": 0,
                  "ftentidentifier": 508184482641,
                  "containerorderingmode": "chronological"
                },
                "508184482641_10102620286347531": {
                  "range": {
                    "offset": 0,
                    "length": 0
                  },
                  "values": [],
                  "count": 0,
                  "ftentidentifier": 508184482641,
                  "containerorderingmode": "chronological"
                },
                "508184482641_10102620290299611": {
                  "range": {
                    "offset": 0,
                    "length": 0
                  },
                  "values": [],
                  "count": 0,
                  "ftentidentifier": 508184482641,
                  "containerorderingmode": "chronological"
                },
                "508184482641_10102620631994851": {
                  "range": {
                    "offset": 0,
                    "length": 0
                  },
                  "values": [],
                  "count": 0,
                  "ftentidentifier": 508184482641,
                  "containerorderingmode": "chronological"
                },
                "508184482641_10102620682568501": {
                  "range": {
                    "offset": 0,
                    "length": 0
                  },
                  "values": [],
                  "count": 0,
                  "ftentidentifier": 508184482641,
                  "containerorderingmode": "chronological"
                },
                "508184482641_10102620805177791": {
                  "range": {
                    "offset": 0,
                    "length": 0
                  },
                  "values": [],
                  "count": 0,
                  "ftentidentifier": 508184482641,
                  "containerorderingmode": "chronological"
                },
                "508184482641_10102620824903261": {
                  "range": {
                    "offset": 0,
                    "length": 0
                  },
                  "values": [],
                  "count": 0,
                  "ftentidentifier": 508184482641,
                  "containerorderingmode": "chronological"
                },
                "508184482641_10102622186260091": {
                  "range": {
                    "offset": 0,
                    "length": 0
                  },
                  "values": [],
                  "count": 0,
                  "ftentidentifier": 508184482641,
                  "containerorderingmode": "chronological"
                },
                "508184482641_10102622190661271": {
                  "range": {
                    "offset": 0,
                    "length": 0
                  },
                  "values": [],
                  "count": 0,
                  "ftentidentifier": 508184482641,
                  "containerorderingmode": "chronological"
                }
              }
            },
            "featuredcommentlists": {
              "comments": null,
              "replies": null
            },
            "servertime": 1459885418
          }
        ],
        []
      ]
    ]
  },
  "css": [
    "ChMB+",
    "6nUJe",
    "GHhcl"
  ],
  "js": [
    "/NqAA",
    "ThKmv",
    "7+Wvj",
    "RVoyp"
  ],
  "bootloadable": {
    "AsyncSignal": {
      "resources": [
        "/NqAA",
        "ChMB+"
      ],
      "module": 1
    },
    "XLinkshimLogController": {
      "resources": [
        "/NqAA",
        "ThKmv",
        "oeUXN"
      ],
      "module": 1
    },
    "ExceptionDialog": {
      "resources": [
        "/NqAA",
        "vjV9S",
        "ChMB+",
        "ThKmv",
        "GHhcl",
        "RVoyp",
        "xRvqJ",
        "M99oK",
        "nyijU",
        "xxecq"
      ],
      "module": 1
    },
    "React": {
      "resources": [
        "RVoyp",
        "ThKmv",
        "/NqAA",
        "ChMB+"
      ],
      "module": 1
    },
    "AsyncDOM": {
      "resources": [
        "/NqAA",
        "ChMB+",
        "kCdR4"
      ],
      "module": 1
    },
    "ConfirmationDialog": {
      "resources": [
        "/NqAA",
        "ChMB+",
        "oE4Do"
      ],
      "module": 1
    },
    "Dialog": {
      "resources": [
        "/NqAA",
        "ThKmv",
        "ChMB+",
        "vjV9S",
        "nyijU",
        "PnFXr"
      ],
      "module": 1
    },
    "QuickSandSolver": {
      "resources": [
        "/NqAA",
        "ChMB+",
        "PNiUp",
        "ccpBO",
        "ThKmv",
        "sHjT1",
        "+ClWy"
      ],
      "module": 1
    },
    "ErrorSignal": {
      "resources": [
        "/NqAA",
        "ChMB+",
        "cNca2"
      ],
      "module": 1
    },
    "ReactDOM": {
      "resources": [
        "RVoyp",
        "ThKmv",
        "/NqAA",
        "ChMB+"
      ],
      "module": 1
    }
  },
  "resource_map": {
    "/NqAA": {
      "type": "js",
      "src": "https://static.xx.fbcdn.net/rsrc.php/v2iWxT3/yx/l/en_GB/HROIdTujVmr.js",
      "crossOrigin": 1
    },
    "ChMB+": {
      "type": "css",
      "src": "https://static.xx.fbcdn.net/rsrc.php/v2/yx/r/k3Q2XVxSzbX.css",
      "permanent": 1,
      "crossOrigin": 1
    },
    "ThKmv": {
      "type": "js",
      "src": "https://static.xx.fbcdn.net/rsrc.php/v2icMq3/yq/l/en_GB/aDAQ5kMH0Pn.js",
      "crossOrigin": 1
    },
    "oeUXN": {
      "type": "js",
      "src": "https://static.xx.fbcdn.net/rsrc.php/v2/yZ/r/aBvqchyj98N.js",
      "crossOrigin": 1
    },
    "vjV9S": {
      "type": "js",
      "src": "https://static.xx.fbcdn.net/rsrc.php/v2iXqO3/yy/l/en_GB/gr9cOlHfR7a.js",
      "crossOrigin": 1
    },
    "GHhcl": {
      "type": "css",
      "src": "https://static.xx.fbcdn.net/rsrc.php/v2/yD/r/M1T65RA6tXh.css",
      "permanent": 1,
      "crossOrigin": 1
    },
    "RVoyp": {
      "type": "js",
      "src": "https://static.xx.fbcdn.net/rsrc.php/v2iwdk3/yW/l/en_GB/1knLCNg5RDa.js",
      "crossOrigin": 1
    },
    "xRvqJ": {
      "type": "js",
      "src": "https://static.xx.fbcdn.net/rsrc.php/v2ixjD3/yL/l/en_GB/G9SciDaoLgv.js",
      "crossOrigin": 1
    },
    "M99oK": {
      "type": "js",
      "src": "https://static.xx.fbcdn.net/rsrc.php/v2i6Fo3/yT/l/en_GB/irADvQCTTxL.js",
      "crossOrigin": 1
    },
    "nyijU": {
      "type": "css",
      "src": "https://static.xx.fbcdn.net/rsrc.php/v2/yi/r/nGIJR7qmC-t.css",
      "permanent": 1,
      "crossOrigin": 1
    },
    "xxecq": {
      "type": "js",
      "src": "https://static.xx.fbcdn.net/rsrc.php/v2iEvA3/y5/l/en_GB/vZhgfyaOfr4.js",
      "crossOrigin": 1
    },
    "kCdR4": {
      "type": "js",
      "src": "https://static.xx.fbcdn.net/rsrc.php/v2/yn/r/JzB2tsQVw-3.js",
      "crossOrigin": 1
    },
    "oE4Do": {
      "type": "js",
      "src": "https://static.xx.fbcdn.net/rsrc.php/v2/yq/r/g65Ifm-JIn6.js",
      "crossOrigin": 1
    },
    "PnFXr": {
      "type": "js",
      "src": "https://static.xx.fbcdn.net/rsrc.php/v2i55M3/yA/l/en_GB/W1TltFpUoyK.js",
      "crossOrigin": 1
    },
    "PNiUp": {
      "type": "js",
      "src": "https://static.xx.fbcdn.net/rsrc.php/v2/ys/r/m5QDGyZX8QU.js",
      "crossOrigin": 1
    },
    "ccpBO": {
      "type": "js",
      "src": "https://static.xx.fbcdn.net/rsrc.php/v2/yn/r/8v2_hdH4Nfm.js",
      "crossOrigin": 1
    },
    "sHjT1": {
      "type": "js",
      "src": "https://static.xx.fbcdn.net/rsrc.php/v2iYut3/yh/l/en_GB/bAxpHI-71D1.js",
      "crossOrigin": 1
    },
    "+ClWy": {
      "type": "js",
      "src": "https://static.xx.fbcdn.net/rsrc.php/v2/yH/r/OJIhOkl_3ZX.js",
      "crossOrigin": 1
    },
    "cNca2": {
      "type": "js",
      "src": "https://static.xx.fbcdn.net/rsrc.php/v2/yz/r/y_UrmQfkNB6.js",
      "crossOrigin": 1
    },
    "7+Wvj": {
      "type": "js",
      "src": "https://static.xx.fbcdn.net/rsrc.php/v2iEXa3/yF/l/en_GB/30wOcs9-aw0.js",
      "crossOrigin": 1
    },
    "6nUJe": {
      "type": "css",
      "src": "https://static.xx.fbcdn.net/rsrc.php/v2/yN/r/aSmjQWDNr6Q.css",
      "permanent": 1,
      "crossOrigin": 1
    }
  },
  "ixData": {},
  "lid": "6270160126885411734"
}
